minitf/__init__.py
minitf/tensor.py
minitf/test_util.py
minitf/variable.py
minitf/autodiff/__init__.py
minitf/autodiff/core.py
minitf/autodiff/gradient_tape.py
minitf/autodiff/graph.py
minitf/autodiff/primitive_vjps.py
minitf/autodiff/tensor.py
minitf/autodiff/util.py
minitf/autodiff/variable.py
minitf/autodiff/vjp_maker.py
minitf/jvps/__init__.py
minitf/jvps/jvp_maker.py
minitf/jvps/primitive_jvps.py
minitf/keras/__init__.py
minitf/keras/activations.py
minitf/keras/initializers.py
minitf/kernal/__init__.py
minitf/kernal/numpy.py
minitf/kernel/__init__.py
minitf/kernel/_cupy.py
minitf/kernel/_numpy.py
minitf/kernel/_numpy_math.py
minitf/kernel/_numpy_random.py
minitf/kernel/core.py
minitf/kernel/cupy.py
minitf/kernel/numpy.py
minitf/kernel/numpy_math.py
minitf/kernel/numpy_random.py
minitf/vjps/__init__.py
minitf/vjps/primitive_vjps.py
minitf/vjps/vjp_maker.py
tests/__init__.py
minitf-0.1.1.4.dist-info/LICENSE
minitf-0.1.1.4.dist-info/METADATA
minitf-0.1.1.4.dist-info/WHEEL
minitf-0.1.1.4.dist-info/top_level.txt
minitf-0.1.1.4.dist-info/RECORD
