Metadata-Version: 2.1
Name: minitf
Version: 0.1.1.4
Summary: Simplified version of Tensorflow for learning purposes.
Home-page: https://github.com/guocuimi/minitf
Author: Michael Mi
Author-email: guocuimi@gmail.com
License: MIT License
Requires-Dist: numpy
Requires-Dist: future
Requires-Dist: matplotlib
